{"version": "1", "message": "ERROR: Hidden Testcases server unreachable.", "problem_id": "ads2_m14_a1_1", "user_id": "Sweety310897", "score": {"sample": {"0": {"execution_time": 0.4421663284301758, "passed": true}, "1": {"execution_time": 0.35974931716918945, "passed": true}, "2": {"execution_time": 0.32802534103393555, "passed": true}, "3": {"execution_time": 0.3454618453979492, "passed": true}, "4": {"execution_time": 0.3287782669067383, "passed": true}, "5": {"execution_time": 0.364426851272583, "passed": true}}}, "check_style_score": "1/1"}