{"version": "1", "message": "ERROR: Hidden Testcases server unreachable.", "problem_id": "ads2_m7_a1_1", "user_id": "Sweety310897", "score": {"sample": {"0": {"execution_time": 0.8476700782775879, "passed": true}, "1": {"execution_time": 0.2110002040863037, "passed": true}, "2": {"execution_time": 0.2821829319000244, "passed": true}, "3": {"execution_time": 0.1873621940612793, "passed": true}, "4": {"execution_time": 0.21410036087036133, "passed": true}, "5": {"execution_time": 0.22592425346374512, "passed": true}}}, "check_style_score": "1/1"}